{
  "gitSyncId": "6904abf885bff76d9e2e3f75_744d6b33-0e33-4c56-ba34-4de2eef33203",
  "id": "Pending Contracts_Auth.getPermissions",
  "pluginId": "js-plugin",
  "pluginType": "JS",
  "unpublishedAction": {
    "actionConfiguration": {
      "encodeParamsToggle": true,
      "jsArguments": [],
      "paginationType": "NONE",
      "timeoutInMillisecond": 10000
    },
    "collectionId": "Pending Contracts_Auth",
    "confirmBeforeExecute": false,
    "datasource": {
      "isAutoGenerated": false,
      "name": "UNUSED_DATASOURCE",
      "pluginId": "js-plugin"
    },
    "dynamicBindingPathList": [
      {
        "key": "body"
      }
    ],
    "fullyQualifiedName": "Auth.getPermissions",
    "name": "getPermissions",
    "pageId": "Pending Contracts",
    "runBehaviour": "MANUAL",
    "userSetOnLoad": false
  }
}